odoo9_addon_mgmtsystem_nonconformity-9.0.1.1.0-py2.7-nspkg.pth
odoo9_addon_mgmtsystem_nonconformity-9.0.1.1.0.dist-info/DESCRIPTION.rst
odoo9_addon_mgmtsystem_nonconformity-9.0.1.1.0.dist-info/METADATA
odoo9_addon_mgmtsystem_nonconformity-9.0.1.1.0.dist-info/RECORD
odoo9_addon_mgmtsystem_nonconformity-9.0.1.1.0.dist-info/WHEEL
odoo9_addon_mgmtsystem_nonconformity-9.0.1.1.0.dist-info/metadata.json
odoo9_addon_mgmtsystem_nonconformity-9.0.1.1.0.dist-info/namespace_packages.txt
odoo9_addon_mgmtsystem_nonconformity-9.0.1.1.0.dist-info/top_level.txt
odoo_addons/mgmtsystem_nonconformity/README.rst
odoo_addons/mgmtsystem_nonconformity/__init__.py
odoo_addons/mgmtsystem_nonconformity/__openerp__.py
odoo_addons/mgmtsystem_nonconformity/data/mail_message_subtype.xml
odoo_addons/mgmtsystem_nonconformity/data/mgmtsystem_nonconformity_cause.xml
odoo_addons/mgmtsystem_nonconformity/data/mgmtsystem_nonconformity_origin.xml
odoo_addons/mgmtsystem_nonconformity/data/mgmtsystem_nonconformity_severity.xml
odoo_addons/mgmtsystem_nonconformity/data/mgmtsystem_nonconformity_stage.xml
odoo_addons/mgmtsystem_nonconformity/data/sequence.xml
odoo_addons/mgmtsystem_nonconformity/demo/mgmtsystem_nonconformity.xml
odoo_addons/mgmtsystem_nonconformity/demo/mgmtsystem_nonconformity_cause.xml
odoo_addons/mgmtsystem_nonconformity/demo/mgmtsystem_nonconformity_origin.xml
odoo_addons/mgmtsystem_nonconformity/i18n/am.po
odoo_addons/mgmtsystem_nonconformity/i18n/ar.po
odoo_addons/mgmtsystem_nonconformity/i18n/bg.po
odoo_addons/mgmtsystem_nonconformity/i18n/bs.po
odoo_addons/mgmtsystem_nonconformity/i18n/ca.po
odoo_addons/mgmtsystem_nonconformity/i18n/ca_ES.po
odoo_addons/mgmtsystem_nonconformity/i18n/cs.po
odoo_addons/mgmtsystem_nonconformity/i18n/da.po
odoo_addons/mgmtsystem_nonconformity/i18n/da_DK.po
odoo_addons/mgmtsystem_nonconformity/i18n/de.po
odoo_addons/mgmtsystem_nonconformity/i18n/el_GR.po
odoo_addons/mgmtsystem_nonconformity/i18n/en_GB.po
odoo_addons/mgmtsystem_nonconformity/i18n/es.po
odoo_addons/mgmtsystem_nonconformity/i18n/es_AR.po
odoo_addons/mgmtsystem_nonconformity/i18n/es_CL.po
odoo_addons/mgmtsystem_nonconformity/i18n/es_CO.po
odoo_addons/mgmtsystem_nonconformity/i18n/es_CR.po
odoo_addons/mgmtsystem_nonconformity/i18n/es_DO.po
odoo_addons/mgmtsystem_nonconformity/i18n/es_EC.po
odoo_addons/mgmtsystem_nonconformity/i18n/es_ES.po
odoo_addons/mgmtsystem_nonconformity/i18n/es_MX.po
