Metadata-Version: 2.0
Name: odoo9-addon-mgmtsystem-nonconformity
Version: 9.0.1.1.0
Summary: Management System - Nonconformity
Home-page: http://www.savoirfairelinux.com
Author: Savoir-faire Linux,Odoo Community Association (OCA)
Author-email: support@odoo-community.org
License: AGPL-3
Platform: UNKNOWN
Classifier: Programming Language :: Python
Classifier: Framework :: Odoo
Classifier: License :: OSI Approved :: GNU Affero General Public License v3
Requires-Python: ~=2.7
Requires-Dist: odoo (<9.1a,>=9.0a)
Requires-Dist: odoo9-addon-document-page-procedure
Requires-Dist: odoo9-addon-mgmtsystem-action
